practice_package.py
testthisqawsedrftg-0.0.1.dist-info/LICENSE.txt
testthisqawsedrftg-0.0.1.dist-info/METADATA
testthisqawsedrftg-0.0.1.dist-info/WHEEL
testthisqawsedrftg-0.0.1.dist-info/top_level.txt
testthisqawsedrftg-0.0.1.dist-info/RECORD
